{"Bottom": [0], "line:": [1], "For": [2], "a": [3, 36, 86, 154], "holistic": [4], "view": [5], "of": [6, 42, 64, 71, 124, 172, 184, 216, 269, 289], "chemical": [7, 43, 57], "engineering": [8, 58], "design,": [9, 73, 175], "this": [10, 106], "book": [11, 21], "provides": [12], "as": [13, 151, 158], "much,": [14], "if": [15], "not": [16], "more,": [17], "than": [18], "any": [19], "other": [20], "available": [22, 321], "on": [23, 99, 142, 167, 194, 205], "the": [24, 47, 62, 68, 307], "topic.'": [25], "Extract": [26], "from": [27, 276, 306], "Chemical": [28, 32], "Engineering": [29, 33], "Resources": [30], "review.": [31], "Design": [34, 49], "is": [35, 85], "complete": [37, 263], "course": [38, 156], "text": [39], "for": [40, 46, 54, 161, 238, 304], "students": [41, 89, 162], "engineering.": [44], "Written": [45], "Senior": [48], "Course,": [50], "and": [51, 67, 77, 81, 98, 116, 133, 136, 145, 178, 190, 199, 212, 221, 231, 242, 247, 251, 257, 264, 295], "also": [52], "suitable": [53], "introduction": [55], "to": [56, 92, 105, 153, 266, 322], "courses,": [59], "it": [60], "covers": [61], "basics": [63], "unit": [65], "operations": [66], "latest": [69, 239], "aspects": [70], "process": [72, 188], "equipment": [74, 143, 195, 225, 270], "selection,": [75, 196], "plant": [76, 174], "operating": [78], "economics,": [79], "safety": [80, 132], "loss": [82], "prevention.": [83], "It": [84], "textbook": [87], "that": [88, 147], "will": [90], "want": [91], "keep": [93], "through": [94], "their": [95, 101], "undergraduate": [96], "education": [97], "into": [100, 111], "professional": [102], "lives.": [103], "-New": [104], "edition:": [107], "*": [108, 260], "Revised": [109], "organization": [110], "Part": [112, 117, 125, 138, 228], "I:": [113], "Process": [114], "Design,": [115], "II:": [118], "Plant": [119], "Design.": [120], "The": [121, 261], "broad": [122], "themes": [123], "I": [126], "are": [127], "flowsheet": [128, 176], "development,": [129], "economic": [130], "analysis,": [131], "environmental": [134], "impact": [135], "optimization.": [137], "II": [139, 229], "contains": [140], "chapters": [141, 193, 226], "design": [144, 168, 198, 249, 274], "selection": [146], "can": [148], "be": [149], "used": [150], "supplements": [152], "lecture": [155, 314], "or": [157, 163], "essential": [159], "references": [160], "practicing": [164], "engineers": [165], "working": [166], "projects.*": [169], "New": [170, 192, 203], "discussion": [171], "conceptual": [173], "development": [177], "revamp": [179], "design*": [180], "Significantly": [181], "increased": [182], "coverage": [183, 215, 268], "capital": [185], "cost": [186], "estimation,": [187], "costing": [189], "economics*": [191], "reactor": [197], "solids": [200], "handling": [201], "processes*": [202, 223], "sections": [204], "fermentation,": [206], "adsorption,": [207], "membrane": [208], "separations,": [209], "ion": [210], "exchange": [211], "chromatography*": [213], "Increased": [214], "batch": [217], "processing,": [218], "food,": [219], "pharmaceutical": [220], "biological": [222], "All": [224], "in": [227], "revised": [230], "updated": [232], "with": [233, 284], "current": [234], "information*": [235], "Updated": [236], "throughout": [237], "US": [240], "codes": [241, 250], "standards,": [243], "including": [244], "API,": [245], "ASME": [246], "ISA": [248], "ANSI": [252], "standards*": [253], "Additional": [254], "worked": [255, 286, 318], "examples": [256], "homework": [258], "problems": [259], "most": [262], "up": [265], "date": [267], "selection*108": [271], "realistic": [272], "commercial": [273], "projects": [275], "diverse": [277], "industries*": [278], "A": [279], "rigorous": [280], "pedagogy": [281], "assists": [282], "learning,": [283], "detailed": [285], "examples,": [287], "end": [288], "chapter": [290], "exercises,": [291], "plus": [292, 299, 316], "supporting": [293], "data": [294], "Excel": [296], "spreadsheet": [297], "calculations": [298], "over": [300], "150": [301], "Patent": [302], "References,": [303], "downloading": [305], "companion": [308], "website*": [309], "Extensive": [310], "instructor": [311], "resources:": [312], "1170": [313], "slides": [315], "fully": [317], "solutions": [319], "manual": [320], "adopting": [323], "instructors": [324]}