{"Contents:": [0], "Preface.": [1], "Introduction": [2], "to": [3, 7], "Research.": [4, 24, 26, 34], "Issues": [5], "Related": [6], "Data": [8, 11], "Gathering.": [9], "Common": [10], "Collection": [12], "Measures.": [13], "Research": [14], "Variables,": [15], "Validity,": [16], "and": [17, 32], "Reliability.": [18], "Designing": [19], "a": [20], "Quantitative": [21, 29], "Study.": [22], "Qualitative": [23], "Classroom": [25], "Coding.": [27], "Analyzing": [28], "Data.": [30], "Concluding": [31], "Reporting": [33], "Appendices.": [35]}