{"Research": [0], "published": [1], "by": [2], "University": [3], "of": [4, 30, 44], "Rochester": [5], "neuroscientists": [6], "C.": [7], "Shawn": [8], "Green": [9], "and": [10, 23, 52], "Daphne": [11], "Bavelier": [12], "has": [13, 26], "grabbed": [14], "national": [15], "attention": [16], "for": [17], "suggesting": [18], "that": [19, 37, 49], "playing": [20], "\"action\"": [21], "video": [22], "computer": [24], "games": [25, 58], "the": [27, 61, 64], "positive": [28], "effect": [29], "enhancing": [31], "student's": [32], "visual": [33], "selective": [34], "attention.": [35], "But": [36], "finding": [38], "is": [39], "just": [40], "one": [41], "small": [42], "part": [43], "a": [45], "more": [46], "important": [47], "message": [48], "all": [50], "parents": [51], "educators": [53], "need": [54], "to": [55, 69], "hear:": [56], "Video": [57], "are": [59], "not": [60], "enemy,": [62], "but": [63], "best": [65], "opportunity": [66], "we": [67], "have": [68], "engage": [70], "our": [71], "kids": [72], "in": [73], "real": [74], "learning.": [75]}