{"<h2>Summary</h2><h3>Background</h3>": [0], "Neurological": [1], "disorders": [2, 195, 226, 259, 431], "are": [3, 368, 387, 397, 420], "increasingly": [4], "recognised": [5], "as": [6, 407], "major": [7, 428], "causes": [8], "of": [9, 16, 23, 41, 63, 65, 143, 145, 152, 166, 171, 200, 211, 219, 269, 282, 341, 355, 366, 385, 395, 404, 413, 427, 452, 458], "death": [10], "and": [11, 26, 38, 45, 57, 69, 77, 89, 101, 116, 147, 149, 169, 207, 221, 233, 247, 254, 266, 271, 276, 293, 298, 326, 332, 373, 380, 390, 422, 424, 444, 472], "disability": [12, 73], "worldwide.": [13], "The": [14, 216, 256, 278, 345, 450], "aim": [15], "this": [17], "analysis": [18], "from": [19, 48, 129, 223], "the": [20, 35, 42, 61, 140, 150, 164, 174, 178, 184, 197, 303, 402, 410, 425, 459], "Global": [21], "Burden": [22], "Diseases,": [24], "Injuries,": [25], "Risk": [27], "Factors": [28], "Study": [29], "(GBD)": [30], "2016": [31], "is": [32, 466], "to": [33, 131, 173, 370, 374, 416, 468], "provide": [34], "most": [36, 457], "comprehensive": [37], "up-to-date": [39], "estimates": [40, 176], "global,": [43], "regional,": [44], "national": [46], "burden": [47, 335, 403, 461], "neurological": [49, 81, 124, 180, 194, 225, 258, 283, 305, 356, 405, 430, 448, 460], "disorders.": [50, 449], "<h3>Methods</h3>": [51], "We": [52, 162], "estimated": [53], "prevalence,": [54], "incidence,": [55, 148], "deaths,": [56], "disability-adjusted": [58], "life-years": [59], "(DALYs;": [60], "sum": [62], "years": [64, 70], "life": [66], "lost": [67], "[YLLs]": [68], "lived": [71], "with": [72, 338, 434], "[YLDs])": [74], "by": [75, 230, 235, 244, 249, 409], "age": [76], "sex": [78], "for": [79, 120, 159, 177, 362, 441, 447, 456], "15": [80, 179], "disorder": [82, 181, 357], "categories": [83, 182], "(tetanus,": [84], "meningitis,": [85, 275], "encephalitis,": [86], "stroke,": [87, 361], "brain": [88, 94], "other": [90, 102, 121, 294, 381], "CNS": [91], "cancers,": [92], "traumatic": [93], "injury,": [95, 98], "spinal": [96], "cord": [97], "Alzheimer's": [99, 292, 378], "disease": [100, 175, 379], "dementias,": [103], "Parkinson's": [104], "disease,": [105], "multiple": [106, 324], "sclerosis,": [107, 325], "motor": [108], "neuron": [109], "diseases,": [110], "idiopathic": [111, 391], "epilepsy,": [112], "migraine,": [113, 323], "tension-type": [114, 327], "headache,": [115], "a": [117, 135, 262, 375], "residual": [118], "category": [119], "less": [122, 342, 352], "common": [123, 331], "disorders)": [125], "in": [126, 192, 264, 313, 316, 336, 349], "195": [127], "countries": [128], "1990": [130, 253], "2016.": [132, 255], "DisMod-MR": [133], "2.1,": [134], "Bayesian": [136], "meta-regression": [137], "tool,": [138], "was": [139, 157], "main": [141], "method": [142], "estimation": [144], "prevalence": [146, 426], "Cause": [151], "Death": [153], "Ensemble": [154], "model": [155], "(CODEm)": [156], "used": [158], "mortality": [160], "estimation.": [161], "quantified": [163, 348], "contribution": [165], "84": [167, 346], "risks": [168, 347, 455], "combinations": [170], "risk": [172, 187, 371, 388, 398], "using": [183], "GBD": [185, 350], "comparative": [186], "assessment": [188], "approach.": [189], "<h3>Findings</h3>": [190], "Globally,": [191, 401], "2016,": [193], "were": [196, 273, 285, 310, 329], "leading": [198, 209], "cause": [199, 210], "DALYs": [201, 222, 234, 248, 272, 284, 367, 386, 396], "(276": [202], "million": [203, 214], "[95%": [204], "UI": [205], "247\u2013308])": [206], "second": [208], "deaths": [212, 220, 270], "(9\u00b70": [213], "[8\u00b78\u20139\u00b74]).": [215], "absolute": [217, 267, 411], "number": [218, 412], "all": [224], "combined": [227, 304], "increased": [228], "(deaths": [229, 243], "39%": [231], "[34\u201344]": [232], "15%": [236], "[9\u201321])": [237], "whereas": [238], "their": [239], "age-standardised": [240, 307], "rates": [241, 265, 309], "decreased": [242], "28%": [245], "[26\u201330]": [246], "27%": [250], "[24\u201331])": [251], "between": [252], "only": [257], "that": [260, 463], "had": [261], "decrease": [263], "numbers": [268], "tetanus,": [274], "encephalitis.": [277], "four": [279], "largest": [280], "contributors": [281], "stroke": [286], "(42\u00b72%": [287], "[38\u00b76\u201346\u00b71]),": [288], "migraine": [289], "(16\u00b73%": [290], "[11\u00b77\u201320\u00b78]),": [291], "dementias": [295, 382], "(10\u00b74%": [296], "[9\u00b70\u201312\u00b71]),": [297], "meningitis": [299], "(7\u00b79%": [300], "[6\u00b76\u201310\u00b74]).": [301], "For": [302], "disorders,": [306, 406], "DALY": [308, 358], "significantly": [311], "higher": [312], "males": [314], "than": [315, 343, 353], "females": [317], "(male-to-female": [318], "ratio": [319], "1\u00b712": [320], "[1\u00b705\u20131\u00b720]),": [321], "but": [322], "headache": [328], "more": [330, 334], "caused": [333], "females,": [337], "male-to-female": [339], "ratios": [340], "0\u00b77.": [344], "explain": [351], "10%": [354], "burdens,": [359], "except": [360], "which": [363], "88\u00b78%": [364], "(86\u00b75\u201390\u00b79)": [365], "attributable": [369], "factors,": [372], "lesser": [376], "extent": [377], "(22\u00b73%": [383], "[11\u00b78\u201335\u00b71]": [384], "attributable)": [389], "epilepsy": [392], "(14\u00b71%": [393], "[10\u00b78\u201317\u00b75]": [394], "attributable).": [399], "<h3>Interpretation</h3>": [400], "measured": [408], "DALYs,": [414], "continues": [415], "increase.": [417], "As": [418], "populations": [419], "growing": [421], "ageing,": [423], "disabling": [429], "steeply": [432], "increases": [433], "age,": [435], "governments": [436], "will": [437], "face": [438], "increasing": [439], "demand": [440], "treatment,": [442], "rehabilitation,": [443], "support": [445], "services": [446], "scarcity": [451], "established": [453], "modifiable": [454], "demonstrates": [462], "new": [464], "knowledge": [465], "required": [467], "develop": [469], "effective": [470], "prevention": [471], "treatment": [473], "strategies.": [474], "<h3>Funding</h3>": [475], "Bill": [476], "&": [477], "Melinda": [478], "Gates": [479], "Foundation.": [480]}