{"Hyperspectral": [0, 14], "image": [1], "(HSI)": [2], "classification": [3, 46, 64, 167], "is": [4, 25, 47, 66, 104, 202], "widely": [5], "used": [6, 31], "for": [7, 36, 44, 98, 208], "the": [8, 28, 62, 80, 102, 115, 131, 141, 147, 150, 158, 187, 205], "analysis": [9], "of": [10, 19, 27, 42, 84, 123, 130, 143, 149, 160], "remotely": [11], "sensed": [12], "images.": [13, 20], "imagery": [15], "includes": [16], "varying": [17], "bands": [18], "Convolutional": [21, 94], "Neural": [22, 95], "Network": [23, 96], "(CNN)": [24], "one": [26], "most": [29], "frequently": [30], "deep": [32, 194], "learning": [33, 195], "based": [34, 57, 196], "methods": [35, 77], "visual": [37], "data": [38], "processing.": [39], "The": [40, 112, 126, 182, 211], "use": [41, 142], "CNN": [43, 82], "HSI": [45, 63, 99, 166, 209], "also": [48], "visible": [49], "in": [50], "recent": [51], "works.": [52], "These": [53], "approaches": [54], "are": [55, 169, 184], "mostly": [56], "on": [58, 69, 128], "2D": [59], "CNN.": [60], "Whereas,": [61], "performance": [65, 159, 201], "highly": [67], "dependent": [68], "both": [70], "spatial": [71, 110, 138], "and": [72, 176], "spectral": [73, 124], "information.": [74], "Very": [75], "few": [76], "have": [78], "utilized": [79], "3D": [81], "because": [83], "increased": [85], "computational": [86], "complexity.": [87], "This": [88], "letter": [89], "proposes": [90], "a": [91, 105, 121], "Hybrid": [92], "Spectral": [93], "(HybridSN)": [97], "classification.": [100, 210], "Basically,": [101], "HybridSN": [103, 207], "spectral-spatial": [106], "3D-CNN": [107, 113, 132, 154], "followed": [108], "by": [109], "2D-CNN.": [111], "facilitates": [114], "joint": [116], "spatial-spectral": [117], "feature": [118], "representation": [119], "from": [120], "stack": [122], "bands.": [125], "2D-CNN": [127], "top": [129], "further": [133], "learns": [134], "more": [135], "abstract": [136], "level": [137], "representation.": [139], "Moreover,": [140], "hybrid": [144, 162], "CNNs": [145], "reduces": [146], "complexity": [148], "model": [151], "compared": [152, 185], "to": [153], "alone.": [155], "To": [156], "test": [157], "this": [161], "approach,": [163], "very": [164, 199], "rigorous": [165], "experiments": [168], "performed": [170], "over": [171], "Indian": [172], "Pines,": [173], "Pavia": [174], "University": [175], "Salinas": [177], "Scene": [178], "remote": [179], "sensing": [180], "datasets.": [181], "results": [183], "with": [186], "state-of-the-art": [188], "hand-crafted": [189], "as": [190, 192], "well": [191], "end-to-end": [193], "methods.": [197], "A": [198], "satisfactory": [200], "obtained": [203], "using": [204], "proposed": [206], "source": [212], "code": [213], "can": [214], "be": [215], "found": [216], "at": [217], "\\url{https://github.com/gokriznastic/HybridSN}.": [218]}