{"Ulcerative": [0], "colitis": [1], "(UC)": [2], "is": [3], "an": [4], "idiopathic": [5], "inflammatory": [6], "disorder.": [7], "These": [8, 78], "guidelines": [9, 38, 79], "indicate": [10], "the": [11, 15, 23, 28, 42, 55, 91], "preferred": [12], "approach": [13, 96], "to": [14, 82, 97], "management": [16], "of": [17, 27, 31, 44, 66], "adults": [18], "with": [19], "UC": [20], "and": [21, 48, 86], "represent": [22], "official": [24], "practice": [25], "recommendations": [26], "American": [29], "College": [30], "Gastroenterology.": [32], "The": [33], "scientific": [34], "evidence": [35, 56], "for": [36, 60], "these": [37], "was": [39, 57, 64], "evaluated": [40], "using": [41, 75], "Grading": [43], "Recommendations": [45], "Assessment,": [46], "Development,": [47], "Evaluation": [49], "(GRADE)": [50], "process.": [51], "In": [52], "instances": [53], "where": [54], "not": [58, 94], "appropriate": [59], "GRADE,": [61], "but": [62, 93], "there": [63], "consensus": [65], "significant": [67], "clinical": [68, 98], "merit,": [69], "\u201ckey": [70], "concept\u201d": [71], "statements": [72], "were": [73], "developed": [74], "expert": [76], "consensus.": [77], "are": [80], "meant": [81], "be": [83, 88], "broadly": [84], "applicable": [85], "should": [87], "viewed": [89], "as": [90], "preferred,": [92], "only,": [95], "scenarios.": [99]}