{"Abstract": [0], "Thirty": [1], "years": [2], "ago,": [3], "Coullet": [4], "et": [5], "al.": [6], "proposed": [7], "that": [8], "a": [9, 41, 45, 54, 58, 65, 70, 81, 96, 100], "special": [10], "optical": [11, 26, 50, 104, 122, 137, 150], "field": [12], "exists": [13], "in": [14, 164], "laser": [15], "cavities": [16], "bearing": [17], "some": [18], "analogy": [19], "with": [20, 44, 57, 72, 169], "the": [21, 34, 117, 161], "superfluid": [22], "vortex.": [23], "Since": [24], "then,": [25], "vortices": [27, 123], "have": [28, 124, 143], "been": [29], "widely": [30], "studied,": [31], "inspired": [32], "by": [33], "hydrodynamics": [35], "sharing": [36], "similar": [37], "mathematics.": [38], "Akin": [39], "to": [40, 64, 132], "fluid": [42], "vortex": [43, 51, 141, 166], "central": [46], "flow": [47], "singularity,": [48], "an": [49], "beam": [52, 71], "has": [53], "phase": [55, 74], "singularity": [56], "certain": [59], "topological": [60], "charge,": [61], "giving": [62], "rise": [63], "hollow": [66], "intensity": [67], "distribution.": [68], "Such": [69], "helical": [73], "fronts": [75], "and": [76, 88, 105, 128, 136, 155], "orbital": [77], "angular": [78], "momentum": [79], "reveals": [80], "subtle": [82], "connection": [83], "between": [84], "macroscopic": [85], "physical": [86, 106], "optics": [87], "microscopic": [89], "quantum": [90, 153], "optics.": [91, 157], "These": [92], "amazing": [93], "properties": [94, 135], "provide": [95], "new": [97], "understanding": [98], "of": [99, 103], "wide": [101], "range": [102], "phenomena,": [107], "including": [108], "twisting": [109], "photons,": [110], "spin\u2013orbital": [111], "interactions,": [112], "Bose\u2013Einstein": [113], "condensates,": [114], "etc.,": [115], "while": [116], "associated": [118], "technologies": [119, 167], "for": [120], "manipulating": [121], "become": [125], "increasingly": [126], "tunable": [127, 140, 165], "flexible.": [129], "Hitherto,": [130], "owing": [131], "these": [133], "salient": [134], "manipulation": [138], "technologies,": [139], "beams": [142], "engendered": [144], "tremendous": [145], "advanced": [146, 171], "applications": [147], "such": [148], "as": [149], "tweezers,": [151], "high-order": [152], "entanglement,": [154], "nonlinear": [156], "This": [158], "article": [159], "reviews": [160], "recent": [162], "progress": [163], "along": [168], "their": [170], "applications.": [172]}