{"The": [0], "outbreak": [1], "of": [2], "coronavirus": [3], "disease": [4], "2019": [5], "(COVID-19)": [6], "in": [7], "Wuhan,": [8], "China,": [9], "is": [10], "serious": [11], "and": [12, 32], "has": [13, 39], "the": [14], "potential": [15], "to": [16, 35], "become": [17], "an": [18], "epidemic": [19], "worldwide.": [20], "Several": [21], "studies": [22], "have": [23], "described": [24], "typical": [25], "clinical": [26], "manifestations": [27], "including": [28], "fever,": [29], "cough,": [30], "diarrhea,": [31], "fatigue.": [33], "However,": [34], "our": [36], "knowledge,": [37], "it": [38], "not": [40], "been": [41], "reported": [42], "that": [43], "patients": [44], "with": [45], "COVID-19": [46], "had": [47], "any": [48], "neurologic": [49], "manifestations.": [50]}