{"The": [0], "COVID-19": [1, 96], "pandemic": [2, 130], "is": [3, 51, 131], "a": [4, 52, 98, 135], "huge": [5], "challenge": [6], "to": [7, 14, 62, 112, 120, 124], "education": [8], "systems.": [9], "This": [10], "Viewpoint": [11, 116], "offers": [12], "guidance": [13], "teachers,": [15], "institutional": [16, 56], "heads,": [17], "and": [18, 34, 43, 49, 66, 92, 100, 133], "officials": [19], "on": [20], "addressing": [21], "the": [22, 30, 83, 122, 129], "crisis.": [23], "What": [24], "preparations": [25], "should": [26, 68, 88], "institutions": [27], "make": [28], "in": [29, 77, 97], "short": [31], "time": [32], "available": [33], "how": [35], "do": [36], "they": [37], "address": [38], "students'": [39, 125], "needs": [40], "by": [41], "level": [42], "field": [44], "of": [45, 55, 71, 137], "study?": [46], "Reassuring": [47], "students": [48], "parents": [50], "vital": [53], "element": [54], "response.": [57], "In": [58], "ramping": [59], "up": [60], "capacity": [61], "teach": [63], "remotely,": [64], "schools": [65], "colleges": [67], "take": [69], "advantage": [70], "asynchronous": [72], "learning,": [73], "which": [74], "works": [75], "best": [76], "digital": [78], "formats.": [79], "As": [80], "well": [81], "as": [82], "normal": [84], "classroom": [85], "subjects,": [86], "teaching": [87], "include": [89], "varied": [90], "assignments": [91], "work": [93], "that": [94], "puts": [95], "global": [99], "historical": [101], "context.": [102], "When": [103], "constructing": [104], "curricula,": [105], "designing": [106], "student": [107], "assessment": [108], "first": [109], "helps": [110], "teachers": [111], "focus.": [113], "Finally,": [114], "this": [115], "suggests": [117], "flexible": [118], "ways": [119], "repair": [121], "damage": [123], "learning": [126], "trajectories": [127], "once": [128], "over": [132], "gives": [134], "list": [136], "resources.": [138]}