{"1.": [0], "Wu": [1], "JT,": [2], "Leung": [3, 5], "K,": [4], "GM.": [6], "Nowcasting": [7], "and": [8, 13], "forecasting": [9], "the": [10, 17], "potential": [11], "domestic": [12], "international": [14], "spread": [15], "of": [16], "2019-nCoV": [18], "outbreak": [19], "originating": [20], "in": [21], "Wuhan,": [22], "China:": [23], "a": [24], "modelling": [25], "study.": [26], "Lancet.": [27], "2020;395(10225):689-697.": [28], "doi:10.1016/S0140-6736(20)30260-9.": [29], "CrossRef": [30], "Google": [31], "Scholar": [32]}