{"Significance": [0], "Drawing": [1], "on": [2, 23, 30, 45, 61], "a": [3], "survey": [4], "of": [5, 19, 35, 68, 75], "more": [6], "than": [7], "5,800": [8], "small": [9, 24, 37], "businesses,": [10, 38], "this": [11], "paper": [12], "provides": [13], "insight": [14], "into": [15], "the": [16, 32, 40, 49, 52, 65, 80], "economic": [17], "impact": [18, 42, 67], "coronavirus": [20], "2019": [21], "(COVID-19)": [22], "businesses.": [25], "The": [26, 56], "results": [27, 57], "shed": [28], "light": [29], "both": [31], "financial": [33], "fragility": [34], "many": [36], "and": [39], "significant": [41], "COVID-19": [43], "had": [44], "these": [46], "businesses": [47], "in": [48], "weeks": [50], "after": [51], "COVID-19\u2013related": [53], "disruptions": [54], "began.": [55], "also": [58], "provide": [59], "evidence": [60], "businesses\u2019": [62], "expectations": [63], "about": [64], "longer-term": [66], "COVID-19,": [69], "as": [70, 72], "well": [71], "their": [73], "perceptions": [74], "relief": [76], "programs": [77], "offered": [78], "by": [79], "government.": [81]}