{"The": [0], "List": [1], "of": [2, 37], "Prokaryotic": [3], "names": [4], "with": [5], "Standing": [6], "in": [7, 12, 27, 33], "Nomenclature": [8], "(LPSN)": [9], "was": [10, 19], "acquired": [11], "November": [13], "2019": [14], "by": [15], "the": [16, 35, 38], "DSMZ": [17], "and": [18, 46], "relaunched": [20], "using": [21], "an": [22], "entirely": [23], "new": [24, 39, 47], "production": [25], "system": [26], "February": [28], "2020.": [29], "This": [30], "article": [31], "describes": [32], "detail": [34], "structure": [36], "site,": [40], "navigation,": [41], "page": [42], "layout,": [43], "search": [44], "facilities": [45], "features.": [48]}