{"CrystalExplorer": [0], "is": [1], "a": [2], "native": [3], "cross-platform": [4], "program": [5], "supported": [6], "on": [7], "Windows,": [8], "MacOS": [9], "and": [10, 18, 30, 35, 58, 72, 75, 91, 107, 110, 116], "Linux": [11], "with": [12, 88], "the": [13, 26, 37, 43, 48, 53, 64, 68, 84, 89, 111], "primary": [14], "function": [15], "of": [16, 20, 39, 47, 98, 119], "visualization": [17, 38], "investigation": [19], "molecular": [21], "crystal": [22, 44], "structures,": [23], "especially": [24], "through": [25, 36], "decorated": [27], "Hirshfeld": [28], "surface": [29], "its": [31], "corresponding": [32], "two-dimensional": [33], "fingerprint,": [34], "void": [40], "spaces": [41], "in": [42], "via": [45], "isosurfaces": [46], "promolecule": [49], "electron": [50], "density.": [51], "Over": [52], "past": [54], "decade,": [55], "significant": [56], "changes": [57], "enhancements": [59], "have": [60], "been": [61], "incorporated": [62], "into": [63], "program,": [65], "such": [66], "as": [67], "capacity": [69], "to": [70, 86, 94], "accurately": [71], "quickly": [73], "calculate": [74, 95], "visualize": [76], "quantitative": [77], "intermolecular": [78], "interactions": [79], "and,": [80], "perhaps": [81], "most": [82], "importantly,": [83], "ability": [85], "interface": [87], "Gaussian": [90], "NWChem": [92], "programs": [93], "quantum-mechanical": [96], "properties": [97], "molecules.": [99], "The": [100], "current": [101], "version,": [102], "CrystalExplorer21": [103], ",": [104], "incorporates": [105], "these": [106], "other": [108], "changes,": [109], "software": [112], "can": [113], "be": [114], "downloaded": [115], "used": [117], "free": [118], "charge": [120], "for": [121], "academic": [122], "research.": [123]}