{"Most": [0], "recent": [1], "semantic": [2, 77], "segmentation": [3, 78, 129], "methods": [4], "adopt": [5], "a": [6, 80, 87, 101, 122, 127], "fully-convolutional": [7], "network": [8], "(FCN)": [9], "with": [10, 27, 121], "an": [11, 72, 98], "encoder-decoder": [12, 59], "architecture.": [13], "The": [14], "encoder": [15, 117], "progressively": [16], "reduces": [17], "the": [18, 38, 46, 58, 106, 114, 144, 162, 166, 174], "spatial": [19], "resolution": [20, 94], "and": [21, 93, 154], "learns": [22], "more": [23], "abstract/semantic": [24], "visual": [25], "concepts": [26], "larger": [28], "receptive": [29, 47], "fields.": [30], "Since": [31], "context": [32, 108], "modeling": [33], "is": [34], "critical": [35], "for": [36], "segmentation,": [37], "latest": [39], "efforts": [40], "have": [41], "been": [42], "focused": [43], "on": [44, 146, 157, 173], "increasing": [45], "field,": [48], "through": [49], "either": [50], "dilated/atrous": [51], "convolutions": [52], "or": [53], "inserting": [54], "attention": [55], "modules.": [56], "However,": [57], "based": [60], "FCN": [61], "architecture": [62], "remains": [63], "unchanged.": [64], "In": [65], "this": [66, 116], "paper,": [67], "we": [68, 85, 160], "aim": [69], "to": [70, 96, 125], "provide": [71, 126], "alternative": [73], "perspective": [74], "by": [75], "treating": [76], "as": [79, 100], "sequence-to-sequence": [81], "prediction": [82], "task.": [83], "Specifically,": [84], "deploy": [86], "pure": [88], "transformer": [89], "(i.e.,": [90], "without": [91], "convolution": [92], "reduction)": [95], "encode": [97], "image": [99], "sequence": [102], "of": [103, 113, 143, 176], "patches.": [104], "With": [105], "global": [107], "modeled": [109], "in": [110, 165], "every": [111], "layer": [112], "transformer,": [115], "can": [118], "be": [119], "combined": [120], "simple": [123], "decoder": [124], "powerful": [128], "model,": [130], "termed": [131], "SEgmentation": [132], "TRansformer": [133], "(SETR).": [134], "Extensive": [135], "experiments": [136], "show": [137], "that": [138], "SETR": [139], "achieves": [140], "new": [141], "state": [142], "art": [145], "ADE20K": [147, 169], "(50.28%": [148], "mIoU),": [149], "Pascal": [150], "Context": [151], "(55.83%": [152], "mIoU)": [153], "competitive": [155, 168], "results": [156], "Cityscapes.": [158], "Particularly,": [159], "achieve": [161], "first": [163], "position": [164], "highly": [167], "test": [170], "server": [171], "leaderboard": [172], "day": [175], "submission.": [177]}