{"Unlike": [0], "previous": [1, 84], "studies": [2], "on": [3, 7, 15, 133], "the": [4, 10, 16, 31, 79, 83, 89, 97, 149, 159, 165], "Metaverse": [5, 12, 44, 76, 98, 167], "based": [6, 14, 132], "Second": [8], "Life,": [9], "current": [11], "is": [13, 45], "social": [17, 66, 169], "value": [18], "of": [19, 34, 64, 75, 151], "Generation": [20], "Z": [21], "that": [22], "online": [23], "and": [24, 40, 68, 91, 105, 107, 114, 136, 145, 154, 161, 172], "offline": [25], "selves": [26], "are": [27], "not": [28], "different.": [29], "With": [30], "technological": [32], "development": [33], "deep": [35], "learning-based": [36], "high-precision": [37], "recognition": [38], "models": [39], "natural": [41], "generation": [42], "models,": [43], "being": [46], "strengthened": [47], "with": [48, 57], "various": [49], "factors,": [50], "from": [51, 82], "mobile-based": [52], "always-on": [53], "access": [54], "to": [55, 122, 138], "connectivity": [56], "reality": [58], "using": [59], "virtual": [60], "currency.": [61], "The": [62], "integration": [63], "enhanced": [65], "activities": [67], "neural-net": [69], "methods": [70, 131], "requires": [71], "a": [72, 124], "new": [73], "definition": [74], "suitable": [77], "for": [78, 95, 163], "present,": [80], "different": [81], "Metaverse.": [85], "This": [86], "paper": [87], "divides": [88], "concepts": [90], "essential": [92, 130], "techniques": [93, 137], "necessary": [94], "realizing": [96], "into": [99], "three": [100, 108, 134], "components": [101, 135], "(i.e.,": [102, 110], "hardware,": [103], "software,": [104], "contents)": [106], "approaches": [109], "user": [111], "interaction,": [112], "implementation,": [113], "application)": [115], "rather": [116], "than": [117], "marketing": [118], "or": [119], "hardware": [120], "approach": [121], "conduct": [123], "comprehensive": [125], "analysis.": [126], "Furthermore,": [127], "we": [128, 157], "describe": [129], "Metaverse's": [139], "representative": [140], "Ready": [141], "Player": [142], "One,": [143], "Roblox,": [144], "Facebook": [146], "research": [147], "in": [148], "domain": [150], "films,": [152], "games,": [153], "studies.": [155], "Finally,": [156], "summarize": [158], "limitations": [160], "directions": [162], "implementing": [164], "immersive": [166], "as": [168], "influences,": [170], "constraints,": [171], "open": [173], "challenges.": [174]}