{"Abstract": [0], "Background": [1], "This": [2, 177], "study": [3, 178], "aims": [4], "to": [5, 36, 133, 191], "examine": [6], "the": [7, 155, 185, 199], "worldwide": [8], "prevalence": [9, 51, 69, 98, 121, 162, 182], "of": [10, 70, 86, 114, 163, 188], "post-coronavirus": [11], "disease": [12], "2019": [13], "(COVID-19)": [14], "condition,": [15], "through": [16], "a": [17, 41, 161], "systematic": [18], "review": [19], "and": [20, 25, 62, 81, 91, 111, 126, 147, 194], "meta-analysis.": [21], "Methods": [22], "PubMed,": [23], "Embase,": [24], "iSearch": [26], "were": [27, 60, 64, 100, 131], "searched": [28], "on": [29, 198], "July": [30], "5,": [31], "2021": [32], "with": [33, 44, 160], "verification": [34], "extending": [35], "March": [37], "13,": [38], "2022.": [39], "Using": [40], "random-effects": [42], "framework": [43], "DerSimonian-Laird": [45], "estimator,": [46], "we": [47], "meta-analyzed": [48], "post-COVID-19": [49, 71, 180], "condition": [50, 72, 181], "at": [52], "28+": [53], "days": [54, 128], "from": [55], "infection.": [56], "Results": [57], "Fifty": [58], "studies": [59], "included,": [61], "41": [63], "meta-analyzed.": [65], "Global": [66, 120], "estimated": [67, 132], "pooled": [68], "was": [73, 154], "0.43": [74], "(95%": [75, 88, 93, 136, 140, 144, 149, 165], "confidence": [76], "interval": [77], "[CI],": [78], ".39\u2013.46).": [79], "Hospitalized": [80], "nonhospitalized": [82], "patients": [83], "had": [84], "estimates": [85, 99], "0.54": [87], "CI,": [89, 94, 104, 109, 118, 137, 141, 145, 150, 166, 174], ".44\u2013.63)": [90], "0.34": [92], ".25\u2013.46),": [95], "respectively.": [96, 152], "Regional": [97], "Asia": [101], "(0.51;": [102], "95%": [103, 108, 117, 173], ".37\u2013.65),": [105], "Europe": [106], "(0.44;": [107], ".32\u2013.56),": [110], "United": [112], "States": [113], "America": [115], "(0.31;": [116], ".21\u2013.43).": [119], "for": [122], "30,": [123], "60,": [124], "90,": [125], "120": [127], "after": [129], "infection": [130], "be": [134, 192], "0.37": [135], ".26\u2013.49),": [138], "0.25": [139], ".15\u2013.38),": [142], "0.32": [143], ".14\u2013.57),": [146], "0.49": [148], ".40\u2013.59),": [151], "Fatigue": [153], "most": [156], "common": [157], "symptom": [158], "reported": [159], "0.23": [164], ".17\u2013.30),": [167], "followed": [168], "by": [169], "memory": [170], "problems": [171], "(0.14;": [172], ".10\u2013.19).": [175], "Conclusions": [176], "finds": [179], "is": [183], "substantial;": [184], "health": [186], "effects": [187], "COVID-19": [189], "seem": [190], "prolonged": [193], "can": [195], "exert": [196], "stress": [197], "healthcare": [200], "system.": [201]}