{"In": [0], "this": [1], "work,": [2], "we": [3, 28, 86, 149], "established": [4], "a": [5, 59, 96, 119, 130, 141], "novel": [6], "theory": [7, 67, 89, 111, 127], "for": [8], "the": [9, 25, 39, 75, 78, 82, 88, 107, 113, 122, 125, 144, 151], "dynamics": [10, 31], "of": [11, 41, 93, 109, 124, 143, 146, 159, 175], "oscillating": [12], "bubbles": [13, 94], "such": [14, 73], "as": [15, 74, 140], "cavitation": [16], "bubbles,": [17, 20], "underwater": [18], "explosion": [19], "and": [21, 54, 61, 81, 102, 105, 161, 164, 173], "air": [22], "bubbles.": [23], "For": [24], "first": [26], "time,": [27], "proposed": [29], "bubble": [30, 43, 49, 71, 154], "equations": [32, 72], "that": [33], "can": [34], "simultaneously": [35], "take": [36], "into": [37, 169], "consideration": [38], "effects": [40], "boundaries,": [42, 101], "interaction,": [44], "ambient": [45, 103], "flow": [46], "field,": [47], "gravity,": [48], "migration,": [50], "fluid": [51], "compressibility,": [52], "viscosity,": [53], "surface": [55], "tension": [56], "while": [57], "maintaining": [58], "unified": [60], "elegant": [62], "mathematical": [63], "form.": [64], "The": [65], "present": [66, 126], "unifies": [68], "different": [69, 136], "classical": [70, 114], "Rayleigh-Plesset": [76], "equation,": [77, 80], "Gilmore": [79], "Keller-Miksis": [83], "equation.": [84], "Furthermore,": [85], "validated": [87], "with": [90, 95, 135, 156], "experimental": [91], "data": [92], "variety": [97], "in": [98], "scales,": [99], "sources,": [100], "conditions": [104], "showed": [106], "advantages": [108], "our": [110, 147], "over": [112], "theoretical": [115], "models,": [116], "followed": [117], "by": [118], "discussion": [120], "on": [121, 129], "applicability": [123], "based": [128], "comparison": [131], "to": [132], "simulation": [133], "results": [134], "numerical": [137], "methods.": [138], "Finally,": [139], "demonstration": [142], "potential": [145], "theory,": [148], "modeled": [150], "complex": [152], "multi-cycle": [153], "interaction": [155], "wide": [157], "ranges": [158], "energy": [160, 171], "phase": [162], "differences": [163], "gained": [165], "new": [166], "physical": [167], "insights": [168], "inter-bubble": [170], "transfer": [172], "coupling": [174], "bubble-induced": [176], "pressure": [177], "waves.": [178]}