{"Applying": [0], "statistical": [1, 56], "concepts": [2, 57], "to": [3, 10, 69, 122], "biological": [4, 90, 105], "scenarios,": [5], "this": [6, 62], "established": [7], "textbook": [8], "continues": [9], "be": [11], "the": [12, 73], "go-to": [13], "tool": [14], "for": [15, 126, 136], "advanced": [16], "undergraduates": [17], "and": [18, 34, 42, 52, 77, 85, 98, 130, 134], "postgraduates": [19], "studying": [20], "biostatistics": [21], "or": [22], "experimental": [23, 78], "design": [24], "in": [25], "biology-related": [26], "areas.": [27, 107], "Chapters": [28], "cover": [29], "linear": [30], "models,": [31, 39], "common": [32], "regression": [33], "ANOVA": [35], "methods,": [36], "mixed": [37], "effects": [38], "model": [40], "selection,": [41], "multivariate": [43], "methods": [44], "used": [45], "by": [46, 111], "biologists,": [47], "requiring": [48], "only": [49], "introductory": [50], "statistics": [51, 76], "basic": [53], "mathematics.": [54], "Demystifying": [55], "with": [58], "clear,": [59], "jargon-free": [60], "explanations,": [61], "new": [63], "edition": [64], "takes": [65], "a": [66, 101], "holistic": [67], "approach": [68], "help": [70, 123], "students": [71], "understand": [72], "relationship": [74], "between": [75], "design.": [79], "Each": [80], "chapter": [81], "contains": [82], "further-reading": [83], "recommendations,": [84], "worked": [86, 128], "examples": [87, 93], "from": [88], "today's": [89], "literature.": [91], "All": [92], "reflect": [94], "modern": [95], "settings,": [96], "methodology": [97], "equipment,": [99], "representing": [100], "wide": [102], "range": [103], "of": [104], "research": [106], "These": [108], "are": [109], "supported": [110], "hands-on": [112], "online": [113], "resources": [114], "including": [115], "real-world": [116], "data": [117], "sets,": [118], "full": [119], "R": [120], "code": [121], "repeat": [124], "analyses": [125], "all": [127], "examples,": [129], "additional": [131], "review": [132], "questions": [133], "exercises": [135], "each": [137], "chapter.": [138]}