{"Common": [0], "challenges": [1], "faced": [2], "by": [3], "lecturers": [4, 42], "teaching": [5, 33], "this": [6, 26], "course": [7], "include": [8], "helping": [9], "students": [10, 68], "learn": [11], "to": [12, 16, 30, 45, 69, 85], "apply": [13], "the": [14, 23, 54, 59, 86], "theory": [15], "practice": [17], "as": [18], "they": [19, 72, 75, 82], "proceed": [20], "with": [21, 61], "research,": [22], "goal": [24], "of": [25, 58], "blended": [27], "approach": [28, 52], "is": [29], "synthesize": [31], "different": [32], "and": [34, 65], "learning": [35], "approaches": [36], "into": [37], "an": [38], "integrated": [39], "mix": [40], "that": [41], "can": [43], "tailor": [44], "their": [46, 78], "own": [47, 79], "specific": [48], "needs.": [49], "An": [50], "innovative": [51], "combines": [53], "face-to-face": [55], "classroom": [56], "methods": [57], "instructor": [60], "computer-based": [62], "activities,": [63], "assignments,": [64], "assessments": [66], "enable": [67], "study": [70], "what": [71], "want,": [73, 76], "when": [74], "at": [77], "pace,": [80], "anywhere": [81], "have": [83], "access": [84], "internet.": [87]}