{"Botanical": [0], "and": [1, 29, 133], "mycological": [2], "herbarium": [3, 9, 47, 58], "(acronym": [4], "TU)": [5], "is": [6], "the": [7, 13, 40, 50, 55, 74, 77, 82, 110, 129, 144, 147, 150], "oldest": [8, 45, 56], "in": [10, 16, 42, 49, 118], "Estonia,": [11], "also": [12, 162], "largest,": [14], "founded": [15], "1802.": [17], "The": [18, 44, 67, 91, 102], "botany": [19], "collection": [20, 51, 152], "holds": [21, 105], "282": [22], "989": [23], "specimens": [24, 33, 106], "of": [25, 34, 76, 79, 88, 113, 153], "vascular": [26], "plants,": [27], "bryophytes": [28], "macroalgae,": [30], "including": [31], "type": [32], "51": [35], "taxa,": [36], "these": [37, 114], "numbers": [38], "describe": [39], "collections": [41, 83, 92, 99, 125], "2014.": [43], "dated": [46, 57], "sheet": [48, 59], "comes": [52, 64], "from": [53, 61, 65, 97, 107, 121, 131, 156, 159, 163], "1819,": [54], "collected": [60, 72], "Estonian": [62, 145], "grounds": [63], "1834.": [66], "materials": [68, 130, 155], "have": [69, 93, 115], "mostly": [70], "been": [71, 85, 116], "by": [73, 95, 119, 139], "staff": [75], "University": [78], "Tartu,": [80], "supplementing": [81], "has": [84], "a": [86], "part": [87], "botanical": [89, 154], "research.": [90], "grown": [94], "donations": [96], "private": [98], "as": [100], "well.": [101], "Herbarium": [103], "Generale": [104], "all": [108], "over": [109], "world,": [111], "many": [112], "taken": [117, 136], "exchange": [120], "other": [122], "herbaria.": [123], "Today": [124], "usually": [126], "grow": [127], "when": [128], "expeditions": [132], "fieldwork": [134], "are": [135], "in,": [137], "less": [138], "exchanges": [140], "or": [141], "donations.": [142], "Of": [143], "herbariums,": [146], "TU": [148], "keeps": [149], "largest": [151], "abroad": [157], "(mostly": [158], "Russia,": [160], "but": [161], "Australia,": [164], "e.g.).": [165]}